silero_advanced/__init__.py
silero_advanced/numText.py
silero_advanced/silero_advanced.py
silero_advanced-1.0.0.dist-info/LICENSE.txt
silero_advanced-1.0.0.dist-info/METADATA
silero_advanced-1.0.0.dist-info/WHEEL
silero_advanced-1.0.0.dist-info/top_level.txt
silero_advanced-1.0.0.dist-info/RECORD
