Metadata-Version: 2.1
Name: silero-advanced
Version: 1.0.0
Summary: Silero-Advanced - это улучшенный модуль Silero.
Home-page: https://github.com/FeeFort/silero-advanced
Author: FeeFort
Author-email: bikov22022006@gmail.com
Project-URL: Documentation, https://github.com/FeeFort/silero-advanced
Keywords: python silero
Classifier: Programming Language :: Python :: 3.10
Classifier: License :: OSI Approved :: MIT License
Classifier: Operating System :: OS Independent
Requires-Python: >=3.7
License-File: LICENSE.txt
Requires-Dist: sounddevice (>=0.4.5)
Requires-Dist: torch (>=1.13.1)
